procore_notification_service_client/__init__.py
procore_notification_service_client/message_property.py
procore_notification_service_client/notification_mode.py
procore_notification_service_client/notification_service_request.py
procore_notification_service_client/notification_service_sender.py
procore_notification_service_client-0.0.3.dist-info/LICENCE
procore_notification_service_client-0.0.3.dist-info/METADATA
procore_notification_service_client-0.0.3.dist-info/WHEEL
procore_notification_service_client-0.0.3.dist-info/top_level.txt
procore_notification_service_client-0.0.3.dist-info/RECORD
