Metadata-Version: 2.1
Name: procore-notification-service-client
Version: 0.0.3
Summary: This library allows to connect to the Procore Notification Service through Python
Author-email: Christian Suarez <christian-suarez-contractor@procore.com>
Project-URL: Homepage, https://github.com/pypa/sampleproject
Classifier: Programming Language :: Python :: 3
Classifier: License :: OSI Approved :: MIT License
Classifier: Operating System :: OS Independent
Requires-Python: >=3.7
License-File: LICENCE
